fastack_mongoengine/__init__.py
fastack_mongoengine/models.py
fastack_mongoengine-0.2.0.dist-info/WHEEL
fastack_mongoengine-0.2.0.dist-info/METADATA
fastack_mongoengine-0.2.0.dist-info/RECORD
