Metadata-Version: 2.1
Name: fastack-mongoengine
Version: 0.2.0
Summary: MongoEngine integration for fastack
Home-page: https://github.com/fastack-dev/fastack-mongoengine
License: MIT
Author: aprilahijriyan
Author-email: 37798612+aprilahijriyan@users.noreply.github.com
Maintainer: aprilahijriyan
Maintainer-email: 37798612+aprilahijriyan@users.noreply.github.com
Requires-Python: >=3.7,<3.10
Classifier: Development Status :: 4 - Beta
Classifier: Environment :: Web Environment
Classifier: Intended Audience :: Developers
Classifier: Intended Audience :: Information Technology
Classifier: Intended Audience :: System Administrators
Classifier: License :: OSI Approved :: MIT License
Classifier: Operating System :: OS Independent
Classifier: Programming Language :: Python
Classifier: Programming Language :: Python :: 3
Classifier: Programming Language :: Python :: 3 :: Only
Classifier: Programming Language :: Python :: 3.7
Classifier: Programming Language :: Python :: 3.8
Classifier: Programming Language :: Python :: 3.9
Classifier: Topic :: Internet
Classifier: Topic :: Software Development
Classifier: Topic :: Software Development :: Libraries
Classifier: Topic :: Software Development :: Libraries :: Python Modules
Requires-Dist: fastack (>=4.0.0,<5.0.0)
Requires-Dist: mongoengine (>=0.23.1,<0.24.0)
Project-URL: Bug Tracker, https://github.com/fastack-dev/fastack-mongoengine/issues
Project-URL: Repository, https://github.com/fastack-dev/fastack-mongoengine
